// 
// Decompiled by Procyon v0.5.36
// 

package agent.human;

import java.security.cert.X509Certificate;
import javax.net.ssl.X509TrustManager;

public class c implements Runnable
{
    private K F;
    public static byte[] ALLATORIxDEMO;
    
    @Override
    public void run() {
        class L implements X509TrustManager
        {
            final /* synthetic */ c ALLATORIxDEMO;
            
            @Override
            public X509Certificate[] getAcceptedIssuers() {
                return null;
            }
            
            @Override
            public void checkClientTrusted(final X509Certificate[] a, final String a) {
            }
            
            L(final c a) {
                this.ALLATORIxDEMO = a;
            }
            
            @Override
            public void checkServerTrusted(final X509Certificate[] a, final String a) {
            }
        }
        // 
        // This method could not be decompiled.
        // 
        // Original Bytecode:
        // 
        //     3: dup            
        //     4: aload_0         /* a */
        //     5: invokespecial   agent/human/L.<init>:(Lagent/human/c;)V
        //     8: astore_1       
        //     9: ldc             "1^."
        //    11: invokestatic    agent/human/K.ALLATORIxDEMO:(Ljava/lang/String;)Ljava/lang/String;
        //    14: invokestatic    javax/net/ssl/SSLContext.getInstance:(Ljava/lang/String;)Ljavax/net/ssl/SSLContext;
        //    17: dup            
        //    18: astore_2       
        //    19: aconst_null    
        //    20: iconst_1       
        //    21: anewarray       Ljavax/net/ssl/TrustManager;
        //    24: iconst_1       
        //    25: dup            
        //    26: pop2           
        //    27: dup            
        //    28: iconst_0       
        //    29: aload_1        
        //    30: aastore        
        //    31: new             Ljava/security/SecureRandom;
        //    34: dup            
        //    35: invokespecial   java/security/SecureRandom.<init>:()V
        //    38: invokevirtual   javax/net/ssl/SSLContext.init:([Ljavax/net/ssl/KeyManager;[Ljavax/net/ssl/TrustManager;Ljava/security/SecureRandom;)V
        //    41: aload_2        
        //    42: invokevirtual   javax/net/ssl/SSLContext.getSocketFactory:()Ljavax/net/ssl/SSLSocketFactory;
        //    45: aload_0         /* a */
        //    46: getfield        agent/human/c.F:Lagent/human/K;
        //    49: invokevirtual   agent/human/K.ALLATORIxDEMO:()Ljava/lang/String;
        //    52: aload_0         /* a */
        //    53: getfield        agent/human/c.F:Lagent/human/K;
        //    56: invokevirtual   agent/human/K.ALLATORIxDEMO:()I
        //    59: invokevirtual   javax/net/ssl/SSLSocketFactory.createSocket:(Ljava/lang/String;I)Ljava/net/Socket;
        //    62: checkcast       Ljavax/net/ssl/SSLSocket;
        //    65: dup            
        //    66: astore_3       
        //    67: sipush          3000
        //    70: invokevirtual   javax/net/ssl/SSLSocket.setSoTimeout:(I)V
        //    73: new             Ljava/io/ObjectOutputStream;
        //    76: dup            
        //    77: aload_3        
        //    78: invokevirtual   javax/net/ssl/SSLSocket.getOutputStream:()Ljava/io/OutputStream;
        //    81: invokespecial   java/io/ObjectOutputStream.<init>:(Ljava/io/OutputStream;)V
        //    84: astore          4
        //    86: new             Ljava/io/ObjectInputStream;
        //    89: dup            
        //    90: aload_3        
        //    91: invokevirtual   javax/net/ssl/SSLSocket.getInputStream:()Ljava/io/InputStream;
        //    94: invokespecial   java/io/ObjectInputStream.<init>:(Ljava/io/InputStream;)V
        //    97: astore          5
        //    99: invokestatic    agent/human/Main.ALLATORIxDEMO:()[B
        //   102: dup            
        //   103: astore          6
        //   105: aload           4
        //   107: dup_x1         
        //   108: dup_x2         
        //   109: aload           6
        //   111: invokevirtual   java/io/ObjectOutputStream.writeObject:(Ljava/lang/Object;)V
        //   114: getstatic       agent/human/c.ALLATORIxDEMO:[B
        //   117: invokestatic    agent/human/Main.ALLATORIxDEMO:([B[B)[B
        //   120: invokevirtual   java/io/ObjectOutputStream.writeObject:(Ljava/lang/Object;)V
        //   123: invokevirtual   java/io/ObjectOutputStream.flush:()V
        //   126: aload           5
        //   128: invokevirtual   java/io/ObjectInputStream.readObject:()Ljava/lang/Object;
        //   131: checkcast       Ljava/lang/Boolean;
        //   134: invokevirtual   java/lang/Boolean.booleanValue:()Z
        //   137: ifeq            177
        //   140: getstatic       java/lang/System.out:Ljava/io/PrintStream;
        //   143: ldc             "VCPBJ\ryBy\nhBk\u000el\u0005!Bo\u0017yBa\rb\t~Ba\u000bf\u0007-\u000byE~Bh\fn\u0010t\u0012y\u0007iL#L"
        //   145: invokestatic    agent/human/K.ALLATORIxDEMO:(Ljava/lang/String;)Ljava/lang/String;
        //   148: invokevirtual   java/io/PrintStream.println:(Ljava/lang/String;)V
        //   151: aload           5
        //   153: invokevirtual   java/io/ObjectInputStream.readObject:()Ljava/lang/Object;
        //   156: checkcast       [B
        //   159: astore          6
        //   161: aload           5
        //   163: invokevirtual   java/io/ObjectInputStream.readObject:()Ljava/lang/Object;
        //   166: checkcast       [B
        //   169: astore          6
        //   171: aload           4
        //   173: goto            190
        //   176: athrow         
        //   177: getstatic       java/lang/System.out:Ljava/io/PrintStream;
        //   180: ldc             "9,?-+-\u0005x\u0007~\u0011-+-\u0006d\u0006cEyBz\u0003c\u0016-\u0003-\u0004a\u0003jL#L"
        //   182: invokestatic    agent/human/K.ALLATORIxDEMO:(Ljava/lang/String;)Ljava/lang/String;
        //   185: invokevirtual   java/io/PrintStream.println:(Ljava/lang/String;)V
        //   188: aload           4
        //   190: invokevirtual   java/io/ObjectOutputStream.close:()V
        //   193: aload_3        
        //   194: aload           5
        //   196: invokevirtual   java/io/ObjectInputStream.close:()V
        //   199: invokevirtual   javax/net/ssl/SSLSocket.close:()V
        //   202: goto            234
        //   205: athrow         
        //   206: astore_2       
        //   207: getstatic       java/lang/System.out:Ljava/io/PrintStream;
        //   210: ldc             "X\fl\u0000a\u0007-\u0016bBn\rc\u0016l\u0001yBe\r~\u0016-X*J"
        //   212: invokestatic    agent/human/K.ALLATORIxDEMO:(Ljava/lang/String;)Ljava/lang/String;
        //   215: invokevirtual   java/io/PrintStream.println:(Ljava/lang/String;)V
        //   218: goto            234
        //   221: astore_2       
        //   222: getstatic       java/lang/System.out:Ljava/io/PrintStream;
        //   225: aload_2        
        //   226: invokedynamic   BootstrapMethod #0, makeConcatWithConstants:(Ljava/lang/Exception;)Ljava/lang/String;
        //   231: invokevirtual   java/io/PrintStream.println:(Ljava/lang/String;)V
        //   234: ldc2_w          60000
        //   237: invokestatic    java/lang/Thread.sleep:(J)V
        //   240: goto            9
        //   243: astore_2       
        //   244: getstatic       java/lang/System.out:Ljava/io/PrintStream;
        //   247: ldc             "D\fy\u0007\u007f\u0010x\u0012y\u0007iN-\nb\u0015-\u0010x\u0006hC"
        //   249: invokestatic    agent/human/K.ALLATORIxDEMO:(Ljava/lang/String;)Ljava/lang/String;
        //   252: invokevirtual   java/io/PrintStream.println:(Ljava/lang/String;)V
        //   255: goto            9
        //    StackMapTable: 00 09 FC 00 09 07 00 09 FF 00 A6 00 00 00 01 07 00 B0 FF 00 00 00 07 07 00 02 07 00 09 07 00 2B 07 00 4D 07 00 53 07 00 5C 07 00 8D 00 00 4C 07 00 53 FF 00 0E 00 00 00 01 07 00 B0 FF 00 00 00 02 07 00 02 07 00 09 00 01 07 00 16 4E 07 00 B2 FC 00 0C 07 00 04 48 07 00 1E
        //    Exceptions:
        //  Try           Handler
        //  Start  End    Start  End    Type                                    
        //  -----  -----  -----  -----  ----------------------------------------
        //  9      176    206    221    Ljava/net/UnknownHostException;
        //  177    202    206    221    Ljava/net/UnknownHostException;
        //  9      176    221    234    Ljava/security/GeneralSecurityException;
        //  177    202    221    234    Ljava/security/GeneralSecurityException;
        //  9      176    221    234    Ljava/lang/ClassNotFoundException;
        //  177    202    221    234    Ljava/lang/ClassNotFoundException;
        //  9      176    221    234    Ljava/io/IOException;
        //  177    202    221    234    Ljava/io/IOException;
        //  234    240    243    258    Ljava/lang/InterruptedException;
        // 
        // The error that occurred was:
        // 
        // java.lang.IllegalStateException: Expression is linked from several locations: Label_0177:
        //     at com.strobel.decompiler.ast.Error.expressionLinkedFromMultipleLocations(Error.java:27)
        //     at com.strobel.decompiler.ast.AstOptimizer.mergeDisparateObjectInitializations(AstOptimizer.java:2596)
        //     at com.strobel.decompiler.ast.AstOptimizer.optimize(AstOptimizer.java:235)
        //     at com.strobel.decompiler.ast.AstOptimizer.optimize(AstOptimizer.java:42)
        //     at com.strobel.decompiler.languages.java.ast.AstMethodBodyBuilder.createMethodBody(AstMethodBodyBuilder.java:214)
        //     at com.strobel.decompiler.languages.java.ast.AstMethodBodyBuilder.createMethodBody(AstMethodBodyBuilder.java:99)
        //     at com.strobel.decompiler.languages.java.ast.AstBuilder.createMethodBody(AstBuilder.java:782)
        //     at com.strobel.decompiler.languages.java.ast.AstBuilder.createMethod(AstBuilder.java:675)
        //     at com.strobel.decompiler.languages.java.ast.AstBuilder.addTypeMembers(AstBuilder.java:552)
        //     at com.strobel.decompiler.languages.java.ast.AstBuilder.createTypeCore(AstBuilder.java:519)
        //     at com.strobel.decompiler.languages.java.ast.AstBuilder.createTypeNoCache(AstBuilder.java:161)
        //     at com.strobel.decompiler.languages.java.ast.AstBuilder.createType(AstBuilder.java:150)
        //     at com.strobel.decompiler.languages.java.ast.AstBuilder.addType(AstBuilder.java:125)
        //     at com.strobel.decompiler.languages.java.JavaLanguage.buildAst(JavaLanguage.java:71)
        //     at com.strobel.decompiler.languages.java.JavaLanguage.decompileType(JavaLanguage.java:59)
        //     at com.strobel.decompiler.DecompilerDriver.decompileType(DecompilerDriver.java:330)
        //     at com.strobel.decompiler.DecompilerDriver.decompileJar(DecompilerDriver.java:251)
        //     at com.strobel.decompiler.DecompilerDriver.main(DecompilerDriver.java:126)
        // 
        throw new IllegalStateException("An error occurred while decompiling this method.");
    }
    
    static {
        c.ALLATORIxDEMO = K.ALLATORIxDEMO("v@j\u0007y=k\u000el\u0005/X=\u001f").getBytes();
    }
    
    public c(final K a) {
        this.F = a;
    }
}